LICENSE
MANIFEST.in
README.md
setup.py
naman/__init__.py
naman.egg-info/PKG-INFO
naman.egg-info/SOURCES.txt
naman.egg-info/dependency_links.txt
naman.egg-info/requires.txt
naman.egg-info/top_level.txt
naman/core/__init__.py
naman/core/admin.py
naman/core/backend.py
naman/core/models.py
naman/core/serializers.py
naman/core/tests.py
naman/core/views.py
naman/core/management/__init__.py
naman/core/management/commands/__init__.py
naman/core/management/commands/sync_vlans.py
naman/core/mappings/__init__.py
naman/core/mappings/vlan_actions.py
naman/core/mappings/vlan_conditions.py
naman/core/pypelib/Condition.py
naman/core/pypelib/Rule.py
naman/core/pypelib/RuleTable.py
naman/core/pypelib/__init__.py
naman/core/pypelib/rules.py
naman/core/pypelib/parsing/ParseEngine.py
naman/core/pypelib/parsing/__init__.py
naman/core/pypelib/parsing/drivers/RegexParser.py
naman/core/pypelib/parsing/drivers/__init__.py
naman/core/pypelib/persistence/PersistenceEngine.py
naman/core/pypelib/persistence/__init__.py
naman/core/pypelib/persistence/backends/__init__.py
naman/core/pypelib/persistence/backends/django/Django.py
naman/core/pypelib/persistence/backends/django/RuleModel.py
naman/core/pypelib/persistence/backends/django/RuleTableModel.py
naman/core/pypelib/persistence/backends/django/__init__.py
naman/core/pypelib/persistence/backends/rawfile/RAWFile.py
naman/core/pypelib/persistence/backends/rawfile/__init__.py
naman/core/pypelib/resolver/Resolver.py
naman/core/pypelib/resolver/__init__.py
naman/core/pypelib/utils/Exceptions.py
naman/core/pypelib/utils/__init__.py
naman/core/tools/__init__.py
naman/core/tools/varios.py
naman/core/tools/views.py
naman/web/__init__.py
naman/web/forms.py
naman/web/settings.py
naman/web/tests.py
naman/web/urls.py
naman/web/views.py
naman/web/views_conflicting_ip.py
naman/web/views_iface.py
naman/web/views_js.py
naman/web/views_machine.py
naman/web/views_service.py
naman/web/views_vlanconfig.py
naman/web/static/ib.png
naman/web/static/css/bootstrap-theme.css
naman/web/static/css/bootstrap-theme.min.css
naman/web/static/css/bootstrap.css
naman/web/static/css/bootstrap.min.css
